compiledcode/__init__.py
compiledcode/cppincludes.py
compiledcode/dwarf/__init__.py
compiledcode/dwarf/dwarf.py
compiledcode/dwarf/dwarf2.py
compiledcode/dwarf/dwarfng.py
compiledcode/elf/__init__.py
compiledcode/elf/elf.py
compiledcode/elf/elfng.py
compiledcode/gwt/__init__.py
compiledcode/javaclass/__init__.py
compiledcode/javaclass/javaclass.ABOUT
compiledcode/javaclass/javaclass.LICENSE
compiledcode/javaclass/javaclass.py
compiledcode/lkmclue/__init__.py
compiledcode/makedepend/__init__.py
compiledcode/sourcecode/__init__.py
compiledcode/sourcecode/kernel.py
compiledcode/sourcecode/metrics.py
compiledcode/sourcecode/source.py
compiledcode-2.1.0.dist-info/METADATA
compiledcode-2.1.0.dist-info/NOTICE
compiledcode-2.1.0.dist-info/README.rst
compiledcode-2.1.0.dist-info/WHEEL
compiledcode-2.1.0.dist-info/apache-2.0.LICENSE
compiledcode-2.1.0.dist-info/entry_points.txt
compiledcode-2.1.0.dist-info/top_level.txt
compiledcode-2.1.0.dist-info/RECORD
